lks_idprovider_fastapi/__init__.py
lks_idprovider_fastapi/dependencies.py
lks_idprovider_fastapi/security.py
lks_idprovider_fastapi-0.1.0.dist-info/METADATA
lks_idprovider_fastapi-0.1.0.dist-info/WHEEL
lks_idprovider_fastapi-0.1.0.dist-info/RECORD
