Metadata-Version: 2.3
Name: lks-idprovider-fastapi
Version: 0.1.0
Summary: Provider-agnostic FastAPI integration for lks-idprovider API protocols.
License: LKSISL
Author: Raul Medeiros
Author-email: rmedeiros@lksnext.com
Requires-Python: >=3.11
Classifier: License :: Other/Proprietary License
Classifier: Programming Language :: Python :: 3
Classifier: Programming Language :: Python :: 3.11
Classifier: Programming Language :: Python :: 3.12
Classifier: Programming Language :: Python :: 3.13
Requires-Dist: fastapi (>=0.116.1)
Requires-Dist: lks-idprovider-api (>=0.1.6,<0.2.0)
